{
  "ok": true,
  "kpiData": [
    {
      "timestamp": "2025-05-10T00:00:00.000Z",
      "session_length": 43.92068099975586
    },
    {
      "timestamp": "2025-05-11T00:00:00.000Z",
      "session_length": 42.4095884958903
    },
    {
      "timestamp": "2025-05-12T00:00:00.000Z",
      "session_length": 48.747205098470054
    },
    {
      "timestamp": "2025-05-13T00:00:00.000Z",
      "session_length": 47.850886265436806
    },
    {
      "timestamp": "2025-05-14T00:00:00.000Z",
      "session_length": 53.148824055989586
    },
    {
      "timestamp": "2025-05-15T00:00:00.000Z",
      "session_length": 50.41000413894653
    },
    {
      "timestamp": "2025-05-16T00:00:00.000Z",
      "session_length": 55.294021129608154
    },
    {
      "timestamp": "2025-05-17T00:00:00.000Z",
      "session_length": 50.947569847106934
    },
    {
      "timestamp": "2025-05-18T00:00:00.000Z",
      "session_length": 53.29202540715536
    },
    {
      "timestamp": "2025-05-19T00:00:00.000Z",
      "session_length": 53.14544860521952
    },
    {
      "timestamp": "2025-05-20T00:00:00.000Z",
      "session_length": 48.61729876200358
    },
    {
      "timestamp": "2025-05-21T00:00:00.000Z",
      "session_length": 59.47325197855631
    },
    {
      "timestamp": "2025-05-22T00:00:00.000Z",
      "session_length": 54.218171993891396
    },
    {
      "timestamp": "2025-05-23T00:00:00.000Z",
      "session_length": 48.99421350161234
    },
    {
      "timestamp": "2025-05-24T00:00:00.000Z",
      "session_length": 46.60136365890503
    },
    {
      "timestamp": "2025-05-25T00:00:00.000Z",
      "session_length": 52.652066707611084
    },
    {
      "timestamp": "2025-05-26T00:00:00.000Z",
      "session_length": 46.40279348691305
    },
    {
      "timestamp": "2025-05-27T00:00:00.000Z",
      "session_length": 50.01197083791097
    },
    {
      "timestamp": "2025-05-28T00:00:00.000Z",
      "session_length": 54.49319267272949
    },
    {
      "timestamp": "2025-05-29T00:00:00.000Z",
      "session_length": 58.57209380467733
    },
    {
      "timestamp": "2025-05-30T00:00:00.000Z",
      "session_length": 51.52371541659037
    },
    {
      "timestamp": "2025-05-31T00:00:00.000Z",
      "session_length": 51.47049148877462
    },
    {
      "timestamp": "2025-06-01T00:00:00.000Z",
      "session_length": 55.10597483317057
    },
    {
      "timestamp": "2025-06-02T00:00:00.000Z",
      "session_length": 53.03246935208639
    },
    {
      "timestamp": "2025-06-03T00:00:00.000Z",
      "session_length": 53.07650089263916
    },
    {
      "timestamp": "2025-06-04T00:00:00.000Z",
      "session_length": 53.10799129803976
    },
    {
      "timestamp": "2025-06-05T00:00:00.000Z",
      "session_length": 55.127960205078125
    },
    {
      "timestamp": "2025-06-06T00:00:00.000Z",
      "session_length": 51.10522699356079
    },
    {
      "timestamp": "2025-06-07T00:00:00.000Z",
      "session_length": 57.072797775268555
    },
    {
      "timestamp": "2025-06-08T00:00:00.000Z",
      "session_length": 57.2613574663798
    },
    {
      "timestamp": "2025-06-09T00:00:00.000Z",
      "session_length": 55.39099486668905
    },
    {
      "timestamp": "2025-06-10T00:00:00.000Z",
      "session_length": 63.96691791216532
    },
    {
      "timestamp": "2025-06-11T00:00:00.000Z",
      "session_length": 60.51116625467936
    },
    {
      "timestamp": "2025-06-12T00:00:00.000Z",
      "session_length": 247.3907889490542
    },
    {
      "timestamp": "2025-06-13T00:00:00.000Z",
      "session_length": 54.401183128356934
    },
    {
      "timestamp": "2025-06-14T00:00:00.000Z",
      "session_length": 55.80601612726847
    },
    {
      "timestamp": "2025-06-15T00:00:00.000Z",
      "session_length": 66.36408042907715
    },
    {
      "timestamp": "2025-06-16T00:00:00.000Z",
      "session_length": 63.42110904057821
    },
    {
      "timestamp": "2025-06-17T00:00:00.000Z",
      "session_length": 58.491062005360924
    },
    {
      "timestamp": "2025-06-18T00:00:00.000Z",
      "session_length": 54.941139459609985
    },
    {
      "timestamp": "2025-06-19T00:00:00.000Z",
      "session_length": 58.79227534929911
    },
    {
      "timestamp": "2025-06-20T00:00:00.000Z",
      "session_length": 63.347237745920815
    },
    {
      "timestamp": "2025-06-21T00:00:00.000Z",
      "session_length": 62.57303285598755
    },
    {
      "timestamp": "2025-06-22T00:00:00.000Z",
      "session_length": 58.271625677744545
    },
    {
      "timestamp": "2025-06-23T00:00:00.000Z",
      "session_length": 56.82674090067545
    },
    {
      "timestamp": "2025-06-24T00:00:00.000Z",
      "session_length": 61.424207051595054
    },
    {
      "timestamp": "2025-06-25T00:00:00.000Z",
      "session_length": 58.48220205307007
    },
    {
      "timestamp": "2025-06-26T00:00:00.000Z",
      "session_length": 51.30759302775065
    },
    {
      "timestamp": "2025-06-27T00:00:00.000Z",
      "session_length": 55.559033473332725
    },
    {
      "timestamp": "2025-06-28T00:00:00.000Z",
      "session_length": 50.79475371042887
    },
    {
      "timestamp": "2025-06-29T00:00:00.000Z",
      "session_length": 54.455845514933266
    },
    {
      "timestamp": "2025-06-30T00:00:00.000Z",
      "session_length": 57.22267039616903
    },
    {
      "timestamp": "2025-07-01T00:00:00.000Z",
      "session_length": 55.60640009244283
    },
    {
      "timestamp": "2025-07-02T00:00:00.000Z",
      "session_length": 51.39356263478597
    },
    {
      "timestamp": "2025-07-03T00:00:00.000Z",
      "session_length": 53.560083866119385
    },
    {
      "timestamp": "2025-07-04T00:00:00.000Z",
      "session_length": 67.98208045959473
    },
    {
      "timestamp": "2025-07-05T00:00:00.000Z",
      "session_length": 54.31863387425741
    },
    {
      "timestamp": "2025-07-06T00:00:00.000Z",
      "session_length": 64.46497090657552
    },
    {
      "timestamp": "2025-07-07T00:00:00.000Z",
      "session_length": 53.31577285130819
    },
    {
      "timestamp": "2025-07-08T00:00:00.000Z",
      "session_length": 67.2652235031128
    },
    {
      "timestamp": "2025-07-09T00:00:00.000Z",
      "session_length": 55.13683064778646
    },
    {
      "timestamp": "2025-07-10T00:00:00.000Z",
      "session_length": 56.90371751785278
    },
    {
      "timestamp": "2025-07-11T00:00:00.000Z",
      "session_length": 55.693523645401
    },
    {
      "timestamp": "2025-07-12T00:00:00.000Z",
      "session_length": 55.41410732269287
    },
    {
      "timestamp": "2025-07-13T00:00:00.000Z",
      "session_length": 52.403716246287026
    },
    {
      "timestamp": "2025-07-14T00:00:00.000Z",
      "session_length": 54.74409278233846
    },
    {
      "timestamp": "2025-07-15T00:00:00.000Z",
      "session_length": 62.65312798817953
    },
    {
      "timestamp": "2025-07-16T00:00:00.000Z",
      "session_length": 53.240294774373375
    },
    {
      "timestamp": "2025-07-17T00:00:00.000Z",
      "session_length": 51.69406747817993
    },
    {
      "timestamp": "2025-07-18T00:00:00.000Z",
      "session_length": 62.24901294708252
    },
    {
      "timestamp": "2025-07-19T00:00:00.000Z",
      "session_length": 55.312313079833984
    },
    {
      "timestamp": "2025-07-20T00:00:00.000Z",
      "session_length": 54.59984747568766
    },
    {
      "timestamp": "2025-07-21T00:00:00.000Z",
      "session_length": 57.696353594462074
    },
    {
      "timestamp": "2025-07-22T00:00:00.000Z",
      "session_length": 54.14272435506185
    },
    {
      "timestamp": "2025-07-23T00:00:00.000Z",
      "session_length": 56.83503739039103
    },
    {
      "timestamp": "2025-07-24T00:00:00.000Z",
      "session_length": 59.64986912409464
    },
    {
      "timestamp": "2025-07-25T00:00:00.000Z",
      "session_length": 54.65425936381022
    },
    {
      "timestamp": "2025-07-26T00:00:00.000Z",
      "session_length": 54.483964125315346
    },
    {
      "timestamp": "2025-07-27T00:00:00.000Z",
      "session_length": 52.352627754211426
    },
    {
      "timestamp": "2025-07-28T00:00:00.000Z",
      "session_length": 55.510145823160805
    },
    {
      "timestamp": "2025-07-29T00:00:00.000Z",
      "session_length": 56.99204651514689
    },
    {
      "timestamp": "2025-07-30T00:00:00.000Z",
      "session_length": 48.675806522369385
    },
    {
      "timestamp": "2025-07-31T00:00:00.000Z",
      "session_length": 55.78698492050171
    },
    {
      "timestamp": "2025-08-01T00:00:00.000Z",
      "session_length": 59.097640673319496
    },
    {
      "timestamp": "2025-08-02T00:00:00.000Z",
      "session_length": 51.95098829269409
    },
    {
      "timestamp": "2025-08-03T00:00:00.000Z",
      "session_length": 52.68051211039225
    },
    {
      "timestamp": "2025-08-04T00:00:00.000Z",
      "session_length": 54.8720494111379
    },
    {
      "timestamp": "2025-08-05T00:00:00.000Z",
      "session_length": 54.54062191645304
    },
    {
      "timestamp": "2025-08-06T00:00:00.000Z",
      "session_length": 55.407548666000366
    },
    {
      "timestamp": "2025-08-07T00:00:00.000Z",
      "session_length": 51.673551400502525
    },
    {
      "timestamp": "2025-08-08T00:00:00.000Z",
      "session_length": 52.16634861628214
    },
    {
      "timestamp": "2025-08-09T00:00:00.000Z",
      "session_length": 53.69821182886759
    },
    {
      "timestamp": "2025-08-10T00:00:00.000Z",
      "session_length": 52.31449031829834
    },
    {
      "timestamp": "2025-08-11T00:00:00.000Z",
      "session_length": 56.267046769460045
    },
    {
      "timestamp": "2025-08-12T00:00:00.000Z",
      "session_length": 52.643473625183105
    },
    {
      "timestamp": "2025-08-13T00:00:00.000Z",
      "session_length": 47.436917304992676
    },
    {
      "timestamp": "2025-08-14T00:00:00.000Z",
      "session_length": 51.175840059916176
    },
    {
      "timestamp": "2025-08-15T00:00:00.000Z",
      "session_length": 50.98443285624186
    },
    {
      "timestamp": "2025-08-16T00:00:00.000Z",
      "session_length": 68.21268447240193
    },
    {
      "timestamp": "2025-08-17T00:00:00.000Z",
      "session_length": 47.450859228769936
    },
    {
      "timestamp": "2025-08-18T00:00:00.000Z",
      "session_length": 52.25585699081421
    },
    {
      "timestamp": "2025-08-19T00:00:00.000Z",
      "session_length": 55.41687401135763
    },
    {
      "timestamp": "2025-08-20T00:00:00.000Z",
      "session_length": 45.897478659947716
    },
    {
      "timestamp": "2025-08-21T00:00:00.000Z",
      "session_length": 45.35231272379557
    },
    {
      "timestamp": "2025-08-22T00:00:00.000Z",
      "session_length": 52.67692947387695
    },
    {
      "timestamp": "2025-08-23T00:00:00.000Z",
      "session_length": 57.21646992365519
    },
    {
      "timestamp": "2025-08-24T00:00:00.000Z",
      "session_length": 53.65615797042847
    },
    {
      "timestamp": "2025-08-25T00:00:00.000Z",
      "session_length": 40.776843229929604
    },
    {
      "timestamp": "2025-08-26T00:00:00.000Z",
      "session_length": 66.94512971242268
    },
    {
      "timestamp": "2025-08-27T00:00:00.000Z",
      "session_length": 43.36441651980082
    },
    {
      "timestamp": "2025-08-28T00:00:00.000Z",
      "session_length": 40.66613451639811
    },
    {
      "timestamp": "2025-08-29T00:00:00.000Z",
      "session_length": 47.10132463773092
    },
    {
      "timestamp": "2025-08-30T00:00:00.000Z",
      "session_length": 40.544021924336754
    },
    {
      "timestamp": "2025-08-31T00:00:00.000Z",
      "session_length": 41.794873078664146
    },
    {
      "timestamp": "2025-09-01T00:00:00.000Z",
      "session_length": 51.02985461552938
    },
    {
      "timestamp": "2025-09-02T00:00:00.000Z",
      "session_length": 45.727379322052
    },
    {
      "timestamp": "2025-09-03T00:00:00.000Z",
      "session_length": 43.28248333930969
    },
    {
      "timestamp": "2025-09-04T00:00:00.000Z",
      "session_length": 44.43886812527975
    },
    {
      "timestamp": "2025-09-05T00:00:00.000Z",
      "session_length": 108.86004002888997
    },
    {
      "timestamp": "2025-09-06T00:00:00.000Z",
      "session_length": 50.476983443550445
    },
    {
      "timestamp": "2025-09-07T00:00:00.000Z",
      "session_length": 106.58652114868164
    },
    {
      "timestamp": "2025-09-08T00:00:00.000Z",
      "session_length": 61.15876488936575
    },
    {
      "timestamp": "2025-09-09T00:00:00.000Z",
      "session_length": 51.99049353599548
    },
    {
      "timestamp": "2025-09-10T00:00:00.000Z",
      "session_length": 71.4608565620754
    },
    {
      "timestamp": "2025-09-11T00:00:00.000Z",
      "session_length": 65.61845092773437
    },
    {
      "timestamp": "2025-09-12T00:00:00.000Z",
      "session_length": 57.74078159332275
    },
    {
      "timestamp": "2025-09-13T00:00:00.000Z",
      "session_length": 52.05983638763428
    },
    {
      "timestamp": "2025-09-14T00:00:00.000Z",
      "session_length": 104.61892301386052
    },
    {
      "timestamp": "2025-09-15T00:00:00.000Z",
      "session_length": 112.9898054816506
    },
    {
      "timestamp": "2025-09-16T00:00:00.000Z",
      "session_length": 88.77129491170247
    },
    {
      "timestamp": "2025-09-17T00:00:00.000Z",
      "session_length": 121.46952999339385
    },
    {
      "timestamp": "2025-09-18T00:00:00.000Z",
      "session_length": 40.77808634440104
    },
    {
      "timestamp": "2025-09-19T00:00:00.000Z",
      "session_length": 51.96122074127197
    },
    {
      "timestamp": "2025-09-20T00:00:00.000Z",
      "session_length": 40.747055390301874
    },
    {
      "timestamp": "2025-09-21T00:00:00.000Z",
      "session_length": 33.688204288482666
    }
  ]
}